CHANGES.rst
LICENSE
MANIFEST.in
README.rst
setup.py
SQLAlchemy_Fixtures.egg-info/PKG-INFO
SQLAlchemy_Fixtures.egg-info/SOURCES.txt
SQLAlchemy_Fixtures.egg-info/dependency_links.txt
SQLAlchemy_Fixtures.egg-info/not-zip-safe
SQLAlchemy_Fixtures.egg-info/requires.txt
SQLAlchemy_Fixtures.egg-info/top_level.txt
docs/Makefile
docs/conf.py
docs/index.rst
docs/make.bat
sqlalchemy_fixtures/__init__.py
tests/__init__.py
tests/test_fixtures.py