Metadata-Version: 1.0
Name: SQLAlchemy-Fixtures
Version: 0.1.6
Summary: Functional fixtures for SQLAlchemy models.
Home-page: https://github.com/kvesteri/sqlalchemy-fixtures
Author: Konsta Vesterinen
Author-email: konsta@fastmonkeys.com
License: BSD
Platform: any
Classifier: Environment :: Web Environment
Classifier: Intended Audience :: Developers
Classifier: License :: OSI Approved :: BSD License
Classifier: Operating System :: OS Independent
Classifier: Programming Language :: Python
Classifier: Topic :: Internet :: WWW/HTTP :: Dynamic Content
Classifier: Topic :: Software Development :: Libraries :: Python Modules
